clusterzeug/README.MD
clusterzeug/__init__.py
clusterzeug/requirements.txt
clusterzeug/thirdparty.json
clusterzeug-0.10.dist-info/LICENSE.rst
clusterzeug-0.10.dist-info/METADATA
clusterzeug-0.10.dist-info/WHEEL
clusterzeug-0.10.dist-info/top_level.txt
clusterzeug-0.10.dist-info/RECORD
